spodcat/__init__.py
spodcat/admin.py
spodcat/admin_inlines.py
spodcat/apps.py
spodcat/filters.py
spodcat/form_fields.py
spodcat/forms.py
spodcat/logging.py
spodcat/markdown.py
spodcat/model_fields.py
spodcat/model_mixin.py
spodcat/podcasting2.py
spodcat/serve_media.py
spodcat/settings.py
spodcat/signals.py
spodcat/time_period.py
spodcat/types.py
spodcat/urls.py
spodcat/utils.py
spodcat/contrib/__init__.py
spodcat/contrib/admin/__init__.py
spodcat/contrib/admin/apps.py
spodcat/contrib/admin/filters.py
spodcat/contrib/admin/mixin.py
spodcat/contrib/admin/site.py
spodcat/contrib/admin/urls.py
spodcat/contrib/admin/views.py
spodcat/contrib/admin/widgets.py
spodcat/data/GeoLite2-ASN.mmdb
spodcat/data/GeoLite2-City.mmdb
spodcat/data/__init__.py
spodcat/locale/sv/LC_MESSAGES/django.mo
spodcat/locale/sv/LC_MESSAGES/django.po
spodcat/logs/__init__.py
spodcat/logs/admin.py
spodcat/logs/apps.py
spodcat/logs/graph_data.py
spodcat/logs/ip_check.py
spodcat/logs/models.py
spodcat/logs/querysets.py
spodcat/logs/user_agent.py
spodcat/logs/management/__init__.py
spodcat/logs/management/commands/__init__.py
spodcat/logs/management/commands/fill_geoips.py
spodcat/logs/management/commands/fill_remote_hosts.py
spodcat/logs/management/commands/rss_request_logs.py
spodcat/logs/migrations/0001_initial.py
spodcat/logs/migrations/__init__.py
spodcat/management/__init__.py
spodcat/management/commands/__init__.py
spodcat/management/commands/get_missing_audio_file_data.py
spodcat/management/commands/import_rss.py
spodcat/management/commands/purge_challenges.py
spodcat/migrations/0001_initial.py
spodcat/migrations/0002_initial.py
spodcat/migrations/0003_podcast_episode_rss_suffix.py
spodcat/migrations/__init__.py
spodcat/models/__init__.py
spodcat/models/artist.py
spodcat/models/category.py
spodcat/models/challenge.py
spodcat/models/comment.py
spodcat/models/episode.py
spodcat/models/episode_chapter.py
spodcat/models/episode_song.py
spodcat/models/font_face.py
spodcat/models/functions.py
spodcat_backend-0.11.0.dist-info/licenses/LICENSE
spodcat_backend-0.11.0.dist-info/METADATA
spodcat_backend-0.11.0.dist-info/WHEEL
spodcat_backend-0.11.0.dist-info/top_level.txt
spodcat_backend-0.11.0.dist-info/RECORD
