Metadata-Version: 2.4
Name: spodcat-backend
Version: 0.11.0
Author-email: Robert Huselius <robert@huseli.us>
License-Expression: GPL-3.0-only
Project-URL: Live example, https://podd.huseli.us
Project-URL: Homepage, https://github.com/Eboreg/spodcat-backend
Project-URL: Issues, https://github.com/Eboreg/spodcat-backend/issues
Project-URL: Source, https://github.com/Eboreg/spodcat-backend
Classifier: Development Status :: 4 - Beta
Classifier: Environment :: Web Environment
Classifier: Framework :: Django
Classifier: Topic :: Internet :: WWW/HTTP :: Dynamic Content :: Content Management System
Classifier: Topic :: Multimedia :: Sound/Audio
Requires-Python: >=3.10
License-File: LICENSE
Requires-Dist: audioop-lts; python_version >= "3.13"
Requires-Dist: country_list
Requires-Dist: django-polymorphic
Requires-Dist: django
Requires-Dist: djangorestframework-jsonapi[django-filter,django-polymorphic]
Requires-Dist: djangorestframework
Requires-Dist: drf-spectacular-jsonapi
Requires-Dist: drf-spectacular
Requires-Dist: feedgen
Requires-Dist: feedparser
Requires-Dist: geoip2
Requires-Dist: iso639-lang
Requires-Dist: klaatu-django
Requires-Dist: markdownify
Requires-Dist: martor
Requires-Dist: pillow
Requires-Dist: pydub
Requires-Dist: python-dateutil
Requires-Dist: python-slugify
Provides-Extra: dev
Requires-Dist: django-debug-toolbar; extra == "dev"
Requires-Dist: django-extensions; extra == "dev"
Requires-Dist: django-storages[azure]; extra == "dev"
Requires-Dist: django-stubs; extra == "dev"
Requires-Dist: djangorestframework-stubs; extra == "dev"
Requires-Dist: flake8; extra == "dev"
Requires-Dist: ipdb; extra == "dev"
Requires-Dist: ipython; extra == "dev"
Requires-Dist: isort; extra == "dev"
Requires-Dist: psycopg[binary]; extra == "dev"
Requires-Dist: pylint-django; extra == "dev"
Requires-Dist: pylint; extra == "dev"
Requires-Dist: python-dotenv; extra == "dev"
Requires-Dist: types-markdown; extra == "dev"
Requires-Dist: types-requests; extra == "dev"
Requires-Dist: whitenoise; extra == "dev"
Dynamic: license-file
